jarvis/__init__.py
jarvis/callbacks.py
jarvis/conversation.py
jarvis/conversation_agent.py
jarvis/jarvis_configuration.py
jarvis/output_parsers.py
jarvis/prompts.py
jarvis/server.py
jarvis/agents/__init__.py
jarvis/agents/conversation_agent.py
jarvis/api/__init__.py
jarvis/api/characters.py
jarvis/api/conversation.py
jarvis/api/knowledge.py
jarvis/api/memory.py
jarvis/api/message_queue.py
jarvis/api/tool.py
jarvis/chains/__init__.py
jarvis/chains/map_reduce.py
jarvis/chains/multiple_conv_retrieve.py
jarvis/chains/reduce.py
jarvis/embeddings/__init__.py
jarvis/embeddings/openai.py
jarvis/exceptions/__init__.py
jarvis/exceptions/api_exceptions.py
jarvis/memories/__init__.py
jarvis/memories/memory_factory.py
jarvis/memories/summary_buffer.py
jarvis/memories/vector_store.py
jarvis/stores/__init__.py
jarvis/stores/agent_profile_store.py
jarvis/stores/entity_store.py
jarvis/stores/knowledge_source_store.py
jarvis/stores/memory_store.py
jarvis/stores/message_history_store.py
jarvis/stores/tool_store.py
jarvis/tools/__init__.py
jarvis/tools/calculator.py
jarvis/utils/__init__.py
jarvis/utils/callbacks.py
jarvis/utils/output_parsers.py
jarvis/vectorstores/__init__.py
jarvis/vectorstores/milvus.py
heliumos_jarvis-0.2.5.dist-info/METADATA
heliumos_jarvis-0.2.5.dist-info/WHEEL
heliumos_jarvis-0.2.5.dist-info/top_level.txt
heliumos_jarvis-0.2.5.dist-info/RECORD
