Metadata-Version: 2.1
Name: heliumos-jarvis
Version: 0.2.5
Summary: AI Agent for heliumos
Classifier: Programming Language :: Python :: 3
Classifier: License :: OSI Approved :: Apache Software License
Requires-Python: >=3.10
Requires-Dist: langchain-core >=0.1.0
Requires-Dist: langserve >=0.0.39
Requires-Dist: langchain-community
Requires-Dist: langchain-openai
Requires-Dist: pydantic-settings
Requires-Dist: fastapi
Requires-Dist: uvicorn
Requires-Dist: pydantic >=2
Requires-Dist: requests
Requires-Dist: tiktoken
Requires-Dist: openai
Requires-Dist: networkx
Requires-Dist: pymilvus
Requires-Dist: psycopg
Requires-Dist: snowflake-id
Requires-Dist: psycopg-binary
Requires-Dist: numexpr
Requires-Dist: pypdf
Requires-Dist: cachetools
Requires-Dist: sse-starlette
